eon_broker_utilities/__init__.py
eon_broker_utilities/fms_service.py
eon_broker_utilities/preproduction_job_consumer.py
eon_broker_utilities-3.6.dist-info/METADATA
eon_broker_utilities-3.6.dist-info/WHEEL
eon_broker_utilities-3.6.dist-info/top_level.txt
eon_broker_utilities-3.6.dist-info/RECORD
