Metadata-Version: 2.1
Name: eon-broker-utilities
Version: 3.6
Home-page: https://bitbucket.org/eon-mes/broker_utilities/src/master
Author: Ahmad Salameh
Author-email: a.salameh@eonaligner.com
License: MIT
Keywords: eon broker project
Requires-Dist: pika (==1.3.0)
Requires-Dist: requests (==2.25.1)
Requires-Dist: eon-logger (==1.0)
